umpire/__init__.py
umpire/cache.py
umpire/config.py
umpire/deploy.py
umpire/fetch.py
umpire/umpire.py
umpire/unpack.py
umpire/update.py
umpire/test/__init__.py
umpire/test/deploy_tests/__init__.py
umpire/test/deploy_tests/tc1_full_deploy.py
umpire/test/deploy_tests/tc2_deploy_from_existing_cache.py
umpire/test/deploy_tests/tc3_fresh_deploy_from_cleared_cache.py
umpire/test/deploy_tests/tc4_existing_deploy_from_cleared_cache.py
umpire/test/deploy_tests/tc5_no_extract_copy.py
umpire/test/deploy_tests/tc6_keep_updated.py
umpire-0.8.2.dist-info/licenses/LICENSE
umpire-0.8.2.dist-info/METADATA
umpire-0.8.2.dist-info/WHEEL
umpire-0.8.2.dist-info/entry_points.txt
umpire-0.8.2.dist-info/top_level.txt
umpire-0.8.2.dist-info/RECORD
